README.md
setup.py
camoco/COB.py
camoco/Camoco.py
camoco/Chrom.py
camoco/Config.py
camoco/Exceptions.py
camoco/Expr.py
camoco/GOnt.py
camoco/GWAS.py
camoco/Genome.py
camoco/Locus.py
camoco/NetComp.py
camoco/Ontology.py
camoco/Overlap.py
camoco/PCCUP.pyx
camoco/RefGen.py
camoco/RefGenDist.pyx
camoco/Term.py
camoco/Tools.py
camoco/__init__.py
camoco.egg-info/PKG-INFO
camoco.egg-info/SOURCES.txt
camoco.egg-info/dependency_links.txt
camoco.egg-info/requires.txt
camoco.egg-info/top_level.txt
camoco/cli/__init__.py
camoco/cli/camoco
camoco/cli/commands/Analysis.py
camoco/cli/commands/__init__.py
camoco/cli/commands/build.py
camoco/cli/commands/cistrans.py
camoco/cli/commands/crossRef.py
camoco/cli/commands/geneneighbors.py
camoco/cli/commands/health.py
camoco/cli/commands/list.py
camoco/cli/commands/locality.py
camoco/cli/commands/plotGWAS.py
camoco/cli/commands/remove.py
camoco/cli/commands/simulateGWAS.py
camoco/cli/commands/snp2gene.py