Metadata-Version: 2.1
Name: camoco
Version: 0.6.4
Summary: Library for Co-Analysis of Molecular Componenets.
Home-page: https://github.com/schae234/camoco
Author: Rob Schaefer
Author-email: rob@linkgae.io
License: Copyright Linkage Analytics 2017, Available under the MIT License
Platform: UNKNOWN
Requires-Python: >=3.6,<3.8
Provides-Extra: docs
